man_spider/__init__.py
man_spider/lib/__init__.py
man_spider/lib/errors.py
man_spider/lib/file.py
man_spider/lib/logger.py
man_spider/lib/parser/__init__.py
man_spider/lib/parser/parser.py
man_spider/lib/processpool.py
man_spider/lib/smb.py
man_spider/lib/spider.py
man_spider/lib/spiderling.py
man_spider/lib/util.py
man_spider/manspider.py
man_spider-1.1.2.dist-info/LICENSE
man_spider-1.1.2.dist-info/METADATA
man_spider-1.1.2.dist-info/WHEEL
man_spider-1.1.2.dist-info/entry_points.txt
man_spider-1.1.2.dist-info/RECORD
