Metadata-Version: 2.3
Name: man-spider
Version: 1.1.2
Summary: Full-featured SMB spider capable of searching file content
License: GPL-3.0
Author: TheTechromancer
Requires-Python: >=3.8,<3.14
Classifier: License :: OSI Approved :: GNU General Public License v3 (GPLv3)
Classifier: Programming Language :: Python :: 3
Classifier: Programming Language :: Python :: 3.8
Classifier: Programming Language :: Python :: 3.9
Classifier: Programming Language :: Python :: 3.10
Classifier: Programming Language :: Python :: 3.11
Classifier: Programming Language :: Python :: 3.12
Classifier: Programming Language :: Python :: 3.13
Requires-Dist: extractous (>=0.3.0,<0.4.0)
Requires-Dist: impacket (>=0.12.0,<0.13.0)
Requires-Dist: python-magic (>=0.4.27,<0.5.0)
